aiplugins/__init__.py
aiplugins/call_api.py
aiplugins/load.py
aiplugins/plugin.py
aiplugins-0.0.4.dist-info/LICENSE
aiplugins-0.0.4.dist-info/METADATA
aiplugins-0.0.4.dist-info/WHEEL
aiplugins-0.0.4.dist-info/RECORD
